ai_commit/__init__.py
ai_commit/ai_commit.py
ai_commit/config.py
ai_commit/config_test.py
ai_commit/default_config.py
py_ai_commit-0.2.0.dist-info/METADATA
py_ai_commit-0.2.0.dist-info/WHEEL
py_ai_commit-0.2.0.dist-info/entry_points.txt
py_ai_commit-0.2.0.dist-info/licenses/LICENSE
py_ai_commit-0.2.0.dist-info/RECORD
