Metadata-Version: 2.3
Name: py-ai-commit
Version: 0.2.0
Summary: Automatic generation of commit messages using AI
Project-URL: Homepage, https://github.com/Ouvill/ai_commit
Project-URL: Issues, https://github.com/Ouvill/ai_commit/issues
Author-email: Ouvill <contact@ouvill.net>
License-File: LICENSE
Requires-Python: >=3.8
Requires-Dist: dataclasses-json>=0.6.7
Requires-Dist: gitpython>=3.1.43
Requires-Dist: langchain-openai>=0.1.20
Requires-Dist: langchain>=0.2.12
Requires-Dist: python-dotenv>=1.0.1
Requires-Dist: tomlkit>=0.13.0
